cool_utils/__init__.py
cool_utils/__main__.py
cool_utils/_missing.py
cool_utils/cache.py
cool_utils/classes.py
cool_utils/compile.py
cool_utils/json_utils.py
cool_utils/links.py
cool_utils/mongo.py
cool_utils/os.py
cool_utils-1.3.2.dist-info/METADATA
cool_utils-1.3.2.dist-info/WHEEL
cool_utils-1.3.2.dist-info/top_level.txt
cool_utils-1.3.2.dist-info/RECORD
