Metadata-Version: 2.1
Name: cool-utils
Version: 1.3.2
Summary: This is Cool Utility tools that you can use in python.
Home-page: https://github.com/Senarc-Studios/Cool-Utils
Author: Benitz Original
Author-email: benitzcoding@yahoo.com
License: BSD
Project-URL: Documentation, https://cool-utils.senarc.org
Project-URL: Issue tracker, https://github.com/Senarc-Studios/Cool-Utils/issues
Project-URL: Github, https://github.com/Senarc-Studios/Cool-Utils/tree/Development
Platform: UNKNOWN
Classifier: Development Status :: 5 - Production/Stable
Classifier: License :: OSI Approved :: BSD License
Classifier: Intended Audience :: Developers
Classifier: Natural Language :: English
Classifier: Operating System :: OS Independent
Classifier: Programming Language :: Python :: 3.7
Classifier: Programming Language :: Python :: 3.8
Classifier: Programming Language :: Python :: 3.9
Classifier: Topic :: Internet
Classifier: Topic :: Software Development :: Libraries
Classifier: Topic :: Software Development :: Libraries :: Python Modules
Classifier: Topic :: Utilities
Requires-Python: >=3.7.0
Requires-Dist: motor
